bookify.py
bookify-1.1.1.dist-info/entry_points.txt
bookify-1.1.1.dist-info/LICENSE
bookify-1.1.1.dist-info/WHEEL
bookify-1.1.1.dist-info/METADATA
bookify-1.1.1.dist-info/RECORD
