Metadata-Version: 2.1
Name: bookify
Version: 1.1.1
Summary: Transform pdf files into books for double-sided printing
License: MIT
Author: Albert
Author-email: github@albert.sh
Requires-Python: >=3.7,<4.0
Classifier: License :: OSI Approved :: MIT License
Classifier: Programming Language :: Python :: 3
Classifier: Programming Language :: Python :: 3.7
Classifier: Programming Language :: Python :: 3.8
Requires-Dist: stapler (==1.0.0b1)
